License.txt
MANIFEST.in
README.md
setup.py
Tibber.egg-info/PKG-INFO
Tibber.egg-info/SOURCES.txt
Tibber.egg-info/dependency_links.txt
Tibber.egg-info/requires.txt
Tibber.egg-info/top_level.txt
test/test.py
tibber/__init__.py
tibber/const.py