Metadata-Version: 1.2
Name: Tibber
Version: 0.16.0
Summary: A python3 library to communicate with Tibber
Home-page: https://github.com/Danielhiversen/pyTibber
Author: Daniel Hjelseth Hoyer
Author-email: mail@dahoiv.net
License: MIT
Platform: UNKNOWN
Classifier: Intended Audience :: Developers
Classifier: Operating System :: OS Independent
Classifier: Programming Language :: Python
Classifier: Programming Language :: Python :: 3
Classifier: Topic :: Home Automation
Classifier: Topic :: Software Development :: Libraries :: Python Modules
Requires-Python: >=3.5.3
